opensips/__init__.py
opensips/version.py
opensips/event/__init__.py
opensips/event/__main__.py
opensips/event/asyncevent.py
opensips/event/datagram.py
opensips/event/event.py
opensips/event/generic_socket.py
opensips/event/handler.py
opensips/event/json_helper.py
opensips/event/stream.py
opensips/mi/__init__.py
opensips/mi/__main__.py
opensips/mi/connection.py
opensips/mi/connector.py
opensips/mi/datagram.py
opensips/mi/fifo.py
opensips/mi/http.py
opensips/mi/jsonrpc_helper.py
opensips-0.1.4.data/data/share/bash_completion/completions/python-opensips
opensips-0.1.4.dist-info/LICENSE
opensips-0.1.4.dist-info/METADATA
opensips-0.1.4.dist-info/WHEEL
opensips-0.1.4.dist-info/entry_points.txt
opensips-0.1.4.dist-info/top_level.txt
opensips-0.1.4.dist-info/RECORD
