Metadata-Version: 2.1
Name: opensips
Version: 0.1.4
Summary: OpenSIPS Python Packages
Home-page: https://github.com/OpenSIPS/python-opensips
Author: Darius Stefan
Author-email: darius.stefan@opensips.org
Classifier: Programming Language :: Python :: 3
Classifier: License :: OSI Approved :: GNU General Public License v3 (GPLv3)
Classifier: Operating System :: OS Independent
Requires-Python: >=3.6
License-File: LICENSE
